{
	"name": "Master Pipeline",
	"properties": {
		"activities": [
			{
				"name": "Incremental Files Ingestion",
				"type": "ExecutePipeline",
				"dependsOn": [],
				"policy": {
					"secureInput": false
				},
				"userProperties": [],
				"typeProperties": {
					"pipeline": {
						"referenceName": "incr_etl_files",
						"type": "PipelineReference"
					},
					"waitOnCompletion": true
				}
			},
			{
				"name": "Load To DB",
				"type": "ExecutePipeline",
				"dependsOn": [
					{
						"activity": "Incremental Files Ingestion",
						"dependencyConditions": [
							"Succeeded"
						]
					}
				],
				"policy": {
					"secureInput": false
				},
				"userProperties": [],
				"typeProperties": {
					"pipeline": {
						"referenceName": "CopyData",
						"type": "PipelineReference"
					},
					"waitOnCompletion": true
				}
			},
			{
				"name": "Archive Files",
				"type": "ExecutePipeline",
				"dependsOn": [
					{
						"activity": "Load To DB",
						"dependencyConditions": [
							"Succeeded"
						]
					}
				],
				"policy": {
					"secureInput": false
				},
				"userProperties": [],
				"typeProperties": {
					"pipeline": {
						"referenceName": "Archive",
						"type": "PipelineReference"
					},
					"waitOnCompletion": true
				}
			}
		],
		"folder": {
			"name": "module_7"
		},
		"annotations": [],
		"lastPublishTime": "2024-03-22T10:49:58Z"
	},
	"type": "Microsoft.DataFactory/factories/pipelines"
}